portfolio_plan/__init__.py
portfolio_plan/_properties.py
portfolio_plan/abc.py
portfolio_plan/const.py
portfolio_plan/core.py
portfolio_plan/errors.py
portfolio_plan/financialseries.py
portfolio_plan/prettyprint.py
portfolio_plan/ratios.py
portfolio_plan/resource.py
portfolio_plan/utils.py
portfolio_plan/visualisation.py
portfolio_plan/data/__init__.py
portfolio_plan/data/_utils.py
portfolio_plan/data/mock.parquet
portfolio_plan/data/mock_cumulative_returns.parquet
portfolio_plan/data/mock_example.parquet
portfolio_plan/data/mock_returns.parquet
portfolio_plan-0.1.0.dist-info/licenses/LICENSE
portfolio_plan-0.1.0.dist-info/METADATA
portfolio_plan-0.1.0.dist-info/WHEEL
portfolio_plan-0.1.0.dist-info/top_level.txt
portfolio_plan-0.1.0.dist-info/RECORD
