Metadata-Version: 2.4
Name: portfolio-plan
Version: 0.1.0
Summary: A Python package for creating, analyzing and visualizing investment strategies. Portfolio-plan allows users to define portfolios with custom asset allocations, simulate investment plans over time periods, calculate returns, and compare historical performance against benchmarks
Author: Alexandre Sonderegger
License-Expression: MIT
Requires-Python: <3.11,>=3.10
License-File: LICENSE
Requires-Dist: empyrical-reloaded>=0.5.10
Requires-Dist: numpy<1.27,>=1.26
Requires-Dist: pandas<2.0.0
Requires-Dist: plotnine>=0.12.4
Requires-Dist: pyarrow<20.0.0
Requires-Dist: yfinance
Dynamic: license-file
